pyqt_titlebar_buttons_widget/__init__.py
pyqt_titlebar_buttons_widget/titlebarButtonsWidget.py
pyqt_titlebar_buttons_widget/ico/__init__.py
pyqt_titlebar_buttons_widget/ico/fold.svg
pyqt_titlebar_buttons_widget/ico/full_screen.svg
pyqt_titlebar_buttons_widget/ico/help.svg
pyqt_titlebar_buttons_widget/ico/search.svg
pyqt_titlebar_buttons_widget/ico/tack.svg
pyqt_titlebar_buttons_widget/ico/unfold.svg
pyqt_titlebar_buttons_widget-0.0.21.dist-info/LICENSE
pyqt_titlebar_buttons_widget-0.0.21.dist-info/METADATA
pyqt_titlebar_buttons_widget-0.0.21.dist-info/WHEEL
pyqt_titlebar_buttons_widget-0.0.21.dist-info/top_level.txt
pyqt_titlebar_buttons_widget-0.0.21.dist-info/RECORD
