Metadata-Version: 2.1
Name: pyqt-titlebar-buttons-widget
Version: 0.0.21
Summary: PyQt buttons (e.g. min/max/close) widget for title bar or menu bar
Home-page: https://github.com/yjg30737/pyqt-titlebar-buttons-widget.git
Author: Jung Gyu Yoon
Author-email: yjg30737@gmail.com
License: MIT
License-File: LICENSE
Requires-Dist: PyQt5 (>=5.8)
Requires-Dist: pyqt-svg-button (>=0.0.1)
